{
  "TargetName": "CoSimServerScenic",
  "SampleTime": 0.01,
  "NoLoopBackMessages": true,
  "TcpPort": 0,
  "IoOutputSignals": [
    {
      "Name": "enable_throttle_cmd",
      "DataType": "float64",
      "PortName": "Ego_Control"
    },
    {
      "Name": "throttle_cmd",
      "DataType": "float64",
      "PortName": "Ego_Control"
    },
    {
      "Name": "enable_brake_cmd",
      "DataType": "float64",
      "PortName": "Ego_Control"
    },
    {
      "Name": "brake_cmd_front",
      "DataType": "float64",
      "PortName": "Ego_Control"
    },
    {
      "Name": "brake_cmd_rear",
      "DataType": "float64",
      "PortName": "Ego_Control"
    },
    {
      "Name": "enable_steering_cmd",
      "DataType": "float64",
      "PortName": "Ego_Control"
    },
    {
      "Name": "steering_cmd_deg",
      "DataType": "float64",
      "PortName": "Ego_Control"
    },
    {
      "Name": "enable_gear_cmd",
      "DataType": "float64",
      "PortName": "Ego_Control"
    },
    {
      "Name": "gear_cmd",
      "DataType": "float64",
      "PortName": "Ego_Control"
    },
    {
      "Name": "Pos_ClutchPedal",
      "DataType": "float64",
      "PortName": "Ego_Control"
    },
    {
      "Name": "v_fellows_external_km_h",
      "DataType": "float64",
      "PortName": "Fellow_Control",
      "Length": 30
    },
    {
      "Name": "d_fellows_external_m",
      "DataType": "float64",
      "PortName": "Fellow_Control",
      "Length": 30
    },
    {
      "Name": "s_fellows_external_m",
      "DataType": "float64",
      "PortName": "Fellow_Control",
      "Length": 30
    }
  ],
  "IoInputSignals": [
    {
      "Name": "Pos_x_Vehicle_CoorSys_E_m",
      "DataType": "float64",
      "PortName": "Ego_State"
    },
    {
      "Name": "Pos_y_Vehicle_CoorSys_E_m",
      "DataType": "float64",
      "PortName": "Ego_State"
    },
    {
      "Name": "Pos_z_Vehicle_CoorSys_E_m",
      "DataType": "float64",
      "PortName": "Ego_State"
    },
    {
      "Name": "Angle_Yaw_Vehicle_CoorSys_E_deg",
      "DataType": "float64",
      "PortName": "Ego_State"
    },
    {
      "Name": "v_x_Vehicle_CoG_m_s",
      "DataType": "float64",
      "PortName": "Ego_State"
    },
    {
      "Name": "v_y_Vehicle_CoG_m_s",
      "DataType": "float64",
      "PortName": "Ego_State"
    },
    {
      "Name": "Ego_Latitude_deg",
      "DataType": "float64",
      "PortName": "Ego_State"
    },
    {
      "Name": "Ego_Longitude_deg",
      "DataType": "float64",
      "PortName": "Ego_State"
    },
    {
      "Name": "Ego_Heading_deg",
      "DataType": "float64",
      "PortName": "Ego_State"
    },
    {
      "Name": "pos_x_V_m",
      "DataType": "float64",
      "PortName": "Fellow_States",
      "Length": 30
    },
    {
      "Name": "pos_y_V_m",
      "DataType": "float64",
      "PortName": "Fellow_States",
      "Length": 30
    },
    {
      "Name": "pos_z_V_m",
      "DataType": "float64",
      "PortName": "Fellow_States",
      "Length": 30
    },
    {
      "Name": "angle_yaw_deg",
      "DataType": "float64",
      "PortName": "Fellow_States",
      "Length": 30
    },
    {
      "Name": "Fellow_Latitude_deg",
      "DataType": "float64",
      "PortName": "Fellow_States",
      "Length": 30
    },
    {
      "Name": "Fellow_Longitude_deg",
      "DataType": "float64",
      "PortName": "Fellow_States",
      "Length": 30
    },
    {
      "Name": "Fellow_Heading_deg",
      "DataType": "float64",
      "PortName": "Fellow_States",
      "Length": 30
    },
    {
      "Name": "velocity_x_y_z_m_s",
      "DataType": "float64",
      "PortName": "Fellow_States",
      "Length": 90
    }
  ]
}